{
    "swagger": "2.0",
    "info": {
        "contact": {}
    },
    "paths": {
        "/health-check": {
            "get": {
                "description": "Health check response",
                "consumes": [
                    "application/json"
                ],
                "produces": [
                    "application/json"
                ],
                "tags": [
                    "health-check"
                ],
                "summary": "Health check response",
                "responses": {
                    "200": {
                        "description": "OK",
                        "schema": {
                            "$ref": "#/definitions/routes.responseMessage"
                        }
                    }
                }
            }
        },
        "/location": {
            "get": {
                "description": "Get all picnic locations",
                "consumes": [
                    "application/json"
                ],
                "produces": [
                    "application/json"
                ],
                "tags": [
                    "location"
                ],
                "summary": "Get all picnic locations",
                "responses": {
                    "200": {
                        "description": "OK",
                        "schema": {
                            "$ref": "#/definitions/routes.responseAllLocation"
                        }
                    },
                    "500": {
                        "description": "Internal Server Error",
                        "schema": {
                            "$ref": "#/definitions/routes.error"
                        }
                    }
                }
            },
            "post": {
                "description": "Add a picnic location",
                "consumes": [
                    "application/json"
                ],
                "produces": [
                    "application/json"
                ],
                "tags": [
                    "location"
                ],
                "summary": "Add a picnic location",
                "parameters": [
                    {
                        "description": "Location Object",
                        "name": "location",
                        "in": "body",
                        "required": true,
                        "schema": {
                            "$ref": "#/definitions/models.PicnicLocationInput"
                        }
                    }
                ],
                "responses": {
                    "201": {
                        "description": "Created",
                        "schema": {
                            "$ref": "#/definitions/routes.responseID"
                        }
                    },
                    "400": {
                        "description": "Bad Request",
                        "schema": {
                            "$ref": "#/definitions/routes.error"
                        }
                    },
                    "500": {
                        "description": "Internal Server Error",
                        "schema": {
                            "$ref": "#/definitions/routes.error"
                        }
                    }
                }
            }
        },
        "/location/{id}": {
            "get": {
                "description": "Get a picnic location by id",
                "consumes": [
                    "application/json"
                ],
                "produces": [
                    "application/json"
                ],
                "tags": [
                    "location"
                ],
                "summary": "Get a picnic location by id",
                "parameters": [
                    {
                        "type": "integer",
                        "description": "Location ID",
                        "name": "id",
                        "in": "path",
                        "required": true
                    }
                ],
                "responses": {
                    "200": {
                        "description": "OK",
                        "schema": {
                            "$ref": "#/definitions/routes.responseOneLocation"
                        }
                    },
                    "400": {
                        "description": "Bad Request",
                        "schema": {
                            "$ref": "#/definitions/routes.error"
                        }
                    },
                    "500": {
                        "description": "Internal Server Error",
                        "schema": {
                            "$ref": "#/definitions/routes.error"
                        }
                    }
                }
            },
            "put": {
                "description": "Update a picnic location by id",
                "consumes": [
                    "application/json"
                ],
                "produces": [
                    "application/json"
                ],
                "tags": [
                    "location"
                ],
                "summary": "Update a picnic location by id",
                "parameters": [
                    {
                        "type": "integer",
                        "description": "Location ID",
                        "name": "id",
                        "in": "path",
                        "required": true
                    },
                    {
                        "description": "Location Object",
                        "name": "location",
                        "in": "body",
                        "required": true,
                        "schema": {
                            "$ref": "#/definitions/models.PicnicLocationInput"
                        }
                    }
                ],
                "responses": {
                    "200": {
                        "description": "OK",
                        "schema": {
                            "$ref": "#/definitions/routes.responseOneLocation"
                        }
                    },
                    "400": {
                        "description": "Bad Request",
                        "schema": {
                            "$ref": "#/definitions/routes.error"
                        }
                    },
                    "500": {
                        "description": "Internal Server Error",
                        "schema": {
                            "$ref": "#/definitions/routes.error"
                        }
                    }
                }
            },
            "delete": {
                "description": "Delete a location by id",
                "consumes": [
                    "application/json"
                ],
                "produces": [
                    "application/json"
                ],
                "tags": [
                    "location"
                ],
                "summary": "Delete a location by id",
                "parameters": [
                    {
                        "type": "integer",
                        "description": "Location ID",
                        "name": "id",
                        "in": "path",
                        "required": true
                    }
                ],
                "responses": {
                    "202": {
                        "description": "Accepted",
                        "schema": {
                            "$ref": "#/definitions/routes.responseMessage"
                        }
                    },
                    "400": {
                        "description": "Bad Request",
                        "schema": {
                            "$ref": "#/definitions/routes.error"
                        }
                    },
                    "500": {
                        "description": "Internal Server Error",
                        "schema": {
                            "$ref": "#/definitions/routes.error"
                        }
                    }
                }
            }
        },
        "/teddy-bear": {
            "get": {
                "description": "Get all teddy bears",
                "consumes": [
                    "application/json"
                ],
                "produces": [
                    "application/json"
                ],
                "tags": [
                    "teddy-bear"
                ],
                "summary": "Get all teddy bears",
                "responses": {
                    "200": {
                        "description": "OK",
                        "schema": {
                            "$ref": "#/definitions/routes.responseAllTeddyBear"
                        }
                    },
                    "500": {
                        "description": "Internal Server Error",
                        "schema": {
                            "$ref": "#/definitions/routes.error"
                        }
                    }
                }
            },
            "post": {
                "description": "Add a teddy bear",
                "consumes": [
                    "application/json"
                ],
                "produces": [
                    "application/json"
                ],
                "tags": [
                    "teddy-bear"
                ],
                "summary": "Add a teddy bear",
                "parameters": [
                    {
                        "description": "Teddy Bear Object",
                        "name": "teddyBear",
                        "in": "body",
                        "required": true,
                        "schema": {
                            "$ref": "#/definitions/models.TeddyBearInput"
                        }
                    }
                ],
                "responses": {
                    "201": {
                        "description": "Created",
                        "schema": {
                            "$ref": "#/definitions/routes.responseID"
                        }
                    },
                    "409": {
                        "description": "Conflict",
                        "schema": {
                            "$ref": "#/definitions/routes.error"
                        }
                    },
                    "422": {
                        "description": "Unprocessable Entity",
                        "schema": {
                            "$ref": "#/definitions/routes.error"
                        }
                    },
                    "500": {
                        "description": "Internal Server Error",
                        "schema": {
                            "$ref": "#/definitions/routes.error"
                        }
                    }
                }
            }
        },
        "/teddy-bear/{name}": {
            "get": {
                "description": "Get a teddy bear by name",
                "consumes": [
                    "application/json"
                ],
                "produces": [
                    "application/json"
                ],
                "tags": [
                    "teddy-bear"
                ],
                "summary": "Get a teddy bear by name",
                "parameters": [
                    {
                        "type": "string",
                        "description": "Teddy Bear Name",
                        "name": "name",
                        "in": "path",
                        "required": true
                    }
                ],
                "responses": {
                    "200": {
                        "description": "OK",
                        "schema": {
                            "$ref": "#/definitions/routes.responseOneTeddyBear"
                        }
                    },
                    "400": {
                        "description": "Bad Request",
                        "schema": {
                            "$ref": "#/definitions/routes.error"
                        }
                    },
                    "500": {
                        "description": "Internal Server Error",
                        "schema": {
                            "$ref": "#/definitions/routes.error"
                        }
                    }
                }
            },
            "put": {
                "description": "Update a teddy bear by name",
                "consumes": [
                    "application/json"
                ],
                "produces": [
                    "application/json"
                ],
                "tags": [
                    "teddy-bear"
                ],
                "summary": "Update a teddy bear by name",
                "parameters": [
                    {
                        "type": "string",
                        "description": "Teddy Bear Name",
                        "name": "name",
                        "in": "path",
                        "required": true
                    },
                    {
                        "description": "Teddy Bear Object",
                        "name": "teddyBear",
                        "in": "body",
                        "required": true,
                        "schema": {
                            "$ref": "#/definitions/models.TeddyBearInput"
                        }
                    }
                ],
                "responses": {
                    "200": {
                        "description": "OK",
                        "schema": {
                            "$ref": "#/definitions/routes.responseOneTeddyBear"
                        }
                    },
                    "422": {
                        "description": "Unprocessable Entity",
                        "schema": {
                            "$ref": "#/definitions/routes.error"
                        }
                    },
                    "500": {
                        "description": "Internal Server Error",
                        "schema": {
                            "$ref": "#/definitions/routes.error"
                        }
                    }
                }
            },
            "delete": {
                "description": "Delete a teddy bear by name",
                "consumes": [
                    "application/json"
                ],
                "produces": [
                    "application/json"
                ],
                "tags": [
                    "teddy-bear"
                ],
                "summary": "Delete a teddy bear by name",
                "parameters": [
                    {
                        "type": "string",
                        "description": "Teddy Bear Name",
                        "name": "name",
                        "in": "path",
                        "required": true
                    }
                ],
                "responses": {
                    "202": {
                        "description": "Accepted",
                        "schema": {
                            "$ref": "#/definitions/routes.responseMessage"
                        }
                    },
                    "404": {
                        "description": "Not Found",
                        "schema": {
                            "$ref": "#/definitions/routes.error"
                        }
                    },
                    "500": {
                        "description": "Internal Server Error",
                        "schema": {
                            "$ref": "#/definitions/routes.error"
                        }
                    }
                }
            }
        }
    },
    "definitions": {
        "models.PicnicLocation": {
            "type": "object",
            "properties": {
                "capacity": {
                    "type": "integer"
                },
                "id": {
                    "type": "integer"
                },
                "location_name": {
                    "type": "string"
                },
                "municipality": {
                    "type": "string"
                }
            }
        },
        "models.PicnicLocationInput": {
            "type": "object",
            "properties": {
                "capacity": {
                    "type": "integer"
                },
                "location_name": {
                    "type": "string"
                },
                "municipality": {
                    "type": "string"
                }
            }
        },
        "models.TeddyBearInput": {
            "type": "object",
            "properties": {
                "accent_color": {
                    "type": "string"
                },
                "characteristic": {
                    "type": "string"
                },
                "is_dressed": {
                    "type": "boolean"
                },
                "name": {
                    "type": "string"
                },
                "owner_name": {
                    "type": "string"
                },
                "picnic_ids": {
                    "type": "array",
                    "items": {
                        "type": "integer"
                    }
                },
                "primary_color": {
                    "type": "string"
                }
            }
        },
        "models.TeddyBearReturn": {
            "type": "object",
            "properties": {
                "accent_color": {
                    "type": "string"
                },
                "characteristic": {
                    "type": "string"
                },
                "id": {
                    "type": "integer"
                },
                "is_dressed": {
                    "type": "boolean"
                },
                "name": {
                    "type": "string"
                },
                "owner_name": {
                    "type": "string"
                },
                "picnic_ids": {
                    "type": "array",
                    "items": {
                        "type": "integer"
                    }
                },
                "primary_color": {
                    "type": "string"
                }
            }
        },
        "routes.error": {
            "type": "object",
            "properties": {
                "error": {
                    "type": "string"
                }
            }
        },
        "routes.responseAllLocation": {
            "type": "object",
            "properties": {
                "locations": {
                    "type": "array",
                    "items": {
                        "$ref": "#/definitions/models.PicnicLocation"
                    }
                }
            }
        },
        "routes.responseAllTeddyBear": {
            "type": "object",
            "properties": {
                "locations": {
                    "type": "array",
                    "items": {
                        "$ref": "#/definitions/models.TeddyBearReturn"
                    }
                }
            }
        },
        "routes.responseID": {
            "type": "object",
            "properties": {
                "object_id": {
                    "type": "integer"
                }
            }
        },
        "routes.responseMessage": {
            "type": "object",
            "properties": {
                "message": {
                    "type": "string"
                }
            }
        },
        "routes.responseOneLocation": {
            "type": "object",
            "properties": {
                "location": {
                    "$ref": "#/definitions/models.PicnicLocation"
                }
            }
        },
        "routes.responseOneTeddyBear": {
            "type": "object",
            "properties": {
                "location": {
                    "$ref": "#/definitions/models.TeddyBearReturn"
                }
            }
        }
    }
}